{"type":"FeatureCollection","name":"summit","crs":{"type":"name","properties":{"name":"urn:ogc:def:crs:OGC:1.3:CRS84"}},"features":[{"type":"Feature","properties":{"src":"DSC02757.jpg"},"geometry":{"type":"Point","coordinates":[142.84701111111113,43.66149722222222]}},{"type":"Feature","properties":{"src":"DSC02698.jpg"},"geometry":{"type":"Point","coordinates":[142.84701111111113,43.66149722222222]}},{"type":"Feature","properties":{"src":"DSC02642.jpg"},"geometry":{"type":"Point","coordinates":[142.83609722222224,43.66067222222222]}},{"type":"Feature","properties":{"src":"DSC02131.jpg"},"geometry":{"type":"Point","coordinates":[142.85404166666666,43.66356111111111]}},{"type":"Feature","properties":{"src":"DSC02127.jpg"},"geometry":{"type":"Point","coordinates":[142.8512361111111,43.661575]}}]}